sinta/__init__.py
sinta/affiliation.py
sinta/affiliation_authors.py
sinta/author.py
sinta/department.py
util/__init__.py
util/config.py
util/utils.py
sinta_scraper-2.2.1.dist-info/LICENSE
sinta_scraper-2.2.1.dist-info/METADATA
sinta_scraper-2.2.1.dist-info/WHEEL
sinta_scraper-2.2.1.dist-info/top_level.txt
sinta_scraper-2.2.1.dist-info/RECORD
