Metadata-Version: 2.1
Name: sinta-scraper
Version: 2.2.1
Summary: Retrieves information from Sinta (Science and Technology Index) via scraping.
Home-page: https://github.com/rendicahya/sinta-scraper
Author: Randy Cahya Wihandika
Author-email: rendicahya@gmail.com
Classifier: Programming Language :: Python :: 3
Classifier: License :: OSI Approved :: GNU General Public License v3 (GPLv3)
Classifier: Operating System :: OS Independent
Requires-Python: >=3.6
License-File: LICENSE
Requires-Dist: beautifulsoup4
Requires-Dist: requests
Requires-Dist: dict2xml
Requires-Dist: python-string-utils
Requires-Dist: flatdict
